tests/__init__.py
tests/data.py
tests/iterations.py
tests/modules.py
tests/steps.py
tests/test_accumulators.py
tests/test_cast.py
tests/test_device.py
tests/test_epochs.py
tests/test_general.py
tests/test_loss.py
tests/test_pytorch.py
tests/test_steps.py
tests/callbacks/__init__.py
tests/callbacks/test_callbacks.py
tests/callbacks/test_tensorboard.py
tests/functional/__init__.py
tests/functional/test_data.py
tests/functional/test_inputs.py
tests/metrics/__init__.py
tests/metrics/test_distance.py
tests/metrics/test_regression.py
tests/metrics/classification/__init__.py
tests/metrics/classification/test_binary.py
tests/metrics/classification/test_multiclass.py
torchtraining/__init__.py
torchtraining/_base.py
torchtraining/_name.py
torchtraining/_version.py
torchtraining/accumulators.py
torchtraining/cast.py
torchtraining/device.py
torchtraining/epochs.py
torchtraining/exceptions.py
torchtraining/iterations.py
torchtraining/loss.py
torchtraining/pytorch.py
torchtraining/quantization.py
torchtraining/steps.py
torchtraining/accelerators/__init__.py
torchtraining/accelerators/horovod.py
torchtraining/callbacks/__init__.py
torchtraining/callbacks/comet.py
torchtraining/callbacks/neptune.py
torchtraining/callbacks/tensorboard.py
torchtraining/functional/__init__.py
torchtraining/functional/data.py
torchtraining/functional/inputs.py
torchtraining/functional/loss.py
torchtraining/functional/utils.py
torchtraining/functional/metrics/__init__.py
torchtraining/functional/metrics/distance.py
torchtraining/functional/metrics/regression.py
torchtraining/functional/metrics/classification/__init__.py
torchtraining/functional/metrics/classification/binary.py
torchtraining/functional/metrics/classification/multiclass.py
torchtraining/functional/metrics/classification/utils/__init__.py
torchtraining/functional/metrics/classification/utils/binary.py
torchtraining/functional/metrics/classification/utils/multiclass.py
torchtraining/metrics/__init__.py
torchtraining/metrics/distance.py
torchtraining_nightly-1604016577.dist-info/LICENSE
torchtraining_nightly-1604016577.dist-info/METADATA
torchtraining_nightly-1604016577.dist-info/WHEEL
torchtraining_nightly-1604016577.dist-info/top_level.txt
torchtraining_nightly-1604016577.dist-info/RECORD
