Metadata-Version: 2.1
Name: torchtraining-nightly
Version: 1604016577
Summary: Functional & flexible neural network training with PyTorch.
Home-page: https://github.com/pypa/torchtraining
Author: Szymon Maszke
Author-email: szymon.maszke@protonmail.com
License: MIT
Project-URL: Website, https://szymonmaszke.github.io/torchtraining
Project-URL: Documentation, https://szymonmaszke.github.io/torchtraining/#torchtraining
Project-URL: Issues, https://github.com/szymonmaszke/torchtraining/issues?q=is%3Aissue+is%3Aopen+sort%3Aupdated-desc
Keywords: pytorch train functional flexible research fit epoch step simple fast
Platform: UNKNOWN
Classifier: Development Status :: 2 - Pre-Alpha
Classifier: Programming Language :: Python
Classifier: Programming Language :: Python :: 3
Classifier: Programming Language :: Python :: 3.6
Classifier: Programming Language :: Python :: 3.7
Classifier: Programming Language :: Python :: 3.8
Classifier: License :: OSI Approved :: MIT License
Classifier: Intended Audience :: Developers
Classifier: Operating System :: OS Independent
Classifier: Topic :: Scientific/Engineering
Classifier: Topic :: Software Development :: Libraries
Classifier: Topic :: Scientific/Engineering :: Artificial Intelligence
Classifier: Topic :: Software Development :: Libraries :: Python Modules
Requires-Python: >=3.6
Requires-Dist: torch (>=1.3.0)
Requires-Dist: loguru (>=0.5.1)
Requires-Dist: rich (>=2.3.0)
Requires-Dist: PyYAML (>=5.3.1)
Provides-Extra: accelerators
Requires-Dist: horovod[pytorch] ; extra == 'accelerators'
Provides-Extra: all
Requires-Dist: horovod[pytorch] ; extra == 'all'
Requires-Dist: tensorboard (>=2.3.0) ; extra == 'all'
Requires-Dist: matplotlib (>=3.3.1) ; extra == 'all'
Requires-Dist: pillow (>=7.2.0) ; extra == 'all'
Requires-Dist: moviepy (>=1.0.3) ; extra == 'all'
Requires-Dist: neptune-client (>=0.4.119) ; extra == 'all'
Requires-Dist: comet-ml (>=3.1.17) ; extra == 'all'
Provides-Extra: callbacks
Requires-Dist: tensorboard (>=2.3.0) ; extra == 'callbacks'
Requires-Dist: matplotlib (>=3.3.1) ; extra == 'callbacks'
Requires-Dist: pillow (>=7.2.0) ; extra == 'callbacks'
Requires-Dist: moviepy (>=1.0.3) ; extra == 'callbacks'
Requires-Dist: neptune-client (>=0.4.119) ; extra == 'callbacks'
Requires-Dist: comet-ml (>=3.1.17) ; extra == 'callbacks'
Provides-Extra: comet
Requires-Dist: comet-ml (>=3.1.17) ; extra == 'comet'
Provides-Extra: horovod
Requires-Dist: horovod[pytorch] ; extra == 'horovod'
Provides-Extra: neptune
Requires-Dist: neptune-client (>=0.4.119) ; extra == 'neptune'
Provides-Extra: tensorboard
Requires-Dist: tensorboard (>=2.3.0) ; extra == 'tensorboard'
Requires-Dist: matplotlib (>=3.3.1) ; extra == 'tensorboard'
Requires-Dist: pillow (>=7.2.0) ; extra == 'tensorboard'
Requires-Dist: moviepy (>=1.0.3) ; extra == 'tensorboard'
Provides-Extra: tests
Requires-Dist: tensorboard (>=2.3.0) ; extra == 'tests'
Requires-Dist: matplotlib (>=3.3.1) ; extra == 'tests'
Requires-Dist: pillow (>=7.2.0) ; extra == 'tests'
Requires-Dist: moviepy (>=1.0.3) ; extra == 'tests'
Requires-Dist: neptune-client (>=0.4.119) ; extra == 'tests'
Requires-Dist: comet-ml (>=3.1.17) ; extra == 'tests'
